yapyfuzz/__init__.py
yapyfuzz/core.py
yapyfuzz/fuzzy.db
yapyfuzz/handler.py
yapy_fuzz-0.1.1.dist-info/LICENSE
yapy_fuzz-0.1.1.dist-info/METADATA
yapy_fuzz-0.1.1.dist-info/WHEEL
yapy_fuzz-0.1.1.dist-info/top_level.txt
yapy_fuzz-0.1.1.dist-info/RECORD
