Metadata-Version: 2.1
Name: yapy-fuzz
Version: 0.1.1
Summary: Python wrapper for junegunn's fuzzyfinder (fzf)
Home-page: https://github.com/harshalchaudhari35/yapy-fuzz
Author: Harshal Chaudhari
Author-email: harshal.chaudhary@gmail.com
License: MIT
Classifier: Development Status :: 4 - Beta
Classifier: Environment :: Console
Classifier: Intended Audience :: Developers
Classifier: License :: OSI Approved :: MIT License
Classifier: Operating System :: OS Independent
Classifier: Programming Language :: Python
Classifier: Topic :: Terminals
License-File: LICENSE
Requires-Dist: pandas
